README.md
setup.cfg
setup.py
Flask_Realtime_Import.egg-info/PKG-INFO
Flask_Realtime_Import.egg-info/SOURCES.txt
Flask_Realtime_Import.egg-info/dependency_links.txt
Flask_Realtime_Import.egg-info/not-zip-safe
Flask_Realtime_Import.egg-info/requires.txt
Flask_Realtime_Import.egg-info/top_level.txt
flask_realtime_import/__init__.py